setup.py
predict_image_mnist/__init__.py
predict_image_mnist/predict_image_mnist.py
predict_image_mnist.egg-info/PKG-INFO
predict_image_mnist.egg-info/SOURCES.txt
predict_image_mnist.egg-info/dependency_links.txt
predict_image_mnist.egg-info/not-zip-safe
predict_image_mnist.egg-info/top_level.txt