Metadata-Version: 2.1
Name: predict-image-mnist
Version: 1.0.0
Summary: predicts the image from to the model specified
Home-page: UNKNOWN
Author: Lokeshwarlakhi
License: UNKNOWN
Platform: UNKNOWN
